{"is_source_file": false, "format": "", "description": "", "external_files": [], "external_methods": [], "published": [], "classes": [], "methods": [], "calls": [], "search-terms": [], "state": 2, "file_id": 13, "knowledge_revision": 28, "git_revision": "4f2d2f9015f5e7e8864780b6cbdcdddb626999cc", "hash": "ebc9e9017510e96e37bd4227a30f445c", "format-version": 4, "code-base-name": "todo_app_frontend", "filename": "todo_app_frontend/src/App.css", "revision_history": [{"28": "4f2d2f9015f5e7e8864780b6cbdcdddb626999cc"}]}